bioimage/__init__.py
bioimage/comparison.py
bioimage/filters.py
bioimage/glowing.py
bioimage/io.py
bioimage-0.1.3.dist-info/LICENSE
bioimage-0.1.3.dist-info/METADATA
bioimage-0.1.3.dist-info/WHEEL
bioimage-0.1.3.dist-info/top_level.txt
bioimage-0.1.3.dist-info/RECORD
