Metadata-Version: 2.1
Name: bioimage
Version: 0.1.3
Summary: bioimage - library to make working with biomedical images more comfortable
Home-page: UNKNOWN
Author: antonkulaga (Anton Kulaga)
Author-email: <antonkulaga@gmail.com>
License: UNKNOWN
Keywords: python,utils,files,bioimages,microscopy,imaging,numpy
Platform: UNKNOWN
Classifier: Development Status :: 2 - Pre-Alpha
Classifier: Intended Audience :: Developers
Classifier: Programming Language :: Python :: 3.9
Classifier: Programming Language :: Python :: 3.10
Classifier: Operating System :: Unix
Classifier: Operating System :: MacOS :: MacOS X
Classifier: Operating System :: Microsoft :: Windows
License-File: LICENSE
Requires-Dist: beartype
Requires-Dist: matplotlib
Requires-Dist: pandas
Requires-Dist: pycomfort
Requires-Dist: more-itertools
Requires-Dist: pims
Requires-Dist: scikit-image
Requires-Dist: jpype1
Requires-Dist: opencv-python
Requires-Dist: tifffile
